Binary.py
Division.py
Roots.py
Scientific_Notation.py
__init__.py
data.py
equations.py
exponents.py
input.py
mc.py
my_math_test.py
primes.py
ScientificNotationAndMore-1.2.0.dist-info/LICENSE.txt
ScientificNotationAndMore-1.2.0.dist-info/METADATA
ScientificNotationAndMore-1.2.0.dist-info/WHEEL
ScientificNotationAndMore-1.2.0.dist-info/top_level.txt
ScientificNotationAndMore-1.2.0.dist-info/RECORD
